{"Exif":{"Lat":0,"Long":0,"Date":"2021-01-30T18:01:02-05:00","Tags":{"ApertureValue":3.356144,"Artist":"Katrina Wallace","ComponentsConfiguration":"","CustomRendered|int":"0","DateTimeDigitized|time.Time":"2021-01-30T18:01:02-05:00","DateTimeOriginal|time.Time":"2021-01-30T18:01:02-05:00","DateTime|time.Time":"2021-01-30T18:01:02-05:00","ExposureTime|*big.Rat":"1/250","FNumber":3.2,"FocalLength":63,"ISOSpeedRatings|int":"1000","LensModel":"RF24-70mm F2.8 L IS USM","Make":"Canon","MaxApertureValue":3,"Model":"Canon EOS R6","Orientation|int":"1","PixelXDimension|int":"2048","PixelYDimension|int":"1365","SceneCaptureType|int":"0","ShutterSpeedValue":7.965783992859268,"Software":"Adobe Photoshop Lightroom Classic 9.4 (Macintosh) (Adobe Photoshop Lightroom Classic 9.4 (Adobe Photoshop Lightroom Classic 9.4 (Macintosh) (Adobe Photoshop Lightroom Classic 9.4 (Macintosh) (Adobe Photoshop Lightroom Classic 9.4 (Adobe Photoshop Ligh","SubSecTime":"820","SubSecTimeDigitized":"820","SubSecTimeOriginal":"820","YCbCrPositioning|int":"1"}}}
